mpyflow/__init__.py
mpyflow/flow.py
mpyflow/measure.py
mpyflow/runtime.py
mpyflow-0.0.1.dist-info/LICENSE
mpyflow-0.0.1.dist-info/METADATA
mpyflow-0.0.1.dist-info/WHEEL
mpyflow-0.0.1.dist-info/RECORD
